todoer/__init__.py
todoer/__main__.py
todoer/database.py
todoer/model.py
todoer/todocli.py
cli_todoer-1.0.9.dist-info/METADATA
cli_todoer-1.0.9.dist-info/WHEEL
cli_todoer-1.0.9.dist-info/entry_points.txt
cli_todoer-1.0.9.dist-info/top_level.txt
cli_todoer-1.0.9.dist-info/RECORD
